discordpy_helper/__init__.py
discordpy_helpme-0.1.dist-info/METADATA
discordpy_helpme-0.1.dist-info/WHEEL
discordpy_helpme-0.1.dist-info/top_level.txt
discordpy_helpme-0.1.dist-info/RECORD
